{
  "name":"张俊",
  "sex":"男",
  "age":"27",
  "exp":"三年半工作经验",
  "nickname":"张俊",
  "firstName":"jun",
  "lastName":"zhang",
  "slogan":"追求专业与卓越前端开发者",
  "location":"WuHan·China",
  "qq":{
    "number":"452064326"
  },
  "website":"",
  "github":"https://zhang452064326.github.io/pcmall/src/html/index.html",
  "email":"zhangjun5753@sina.com",
  "intro":[
    "懂产品，会设计，熟练DIV+CSS+Javascript,以及HTML5+CSS3新特性、根据设计图完成页面制作。熟练和习惯JQ的开发模式。熟悉angularJs常用scss和gulp。",
    "善于学习。善于发现和解决重复性的影响做事效率的问题。喜欢设计，对用户体验有追求。爱折腾，没事的时候喜欢做点小东西。"
  ],
  "experience":[
    {
      "time":"2014年10-今",
      "title":"义乌风度网络科技有限公司",
      "intro":"前端开发",
      "description":"期间，大部分精力都用于钻研和探索前端的工程化。代码从css转到less，从less转到scss。学习了nodejs，熟悉了gulp。基于gulp做了很多前端自动化构建的工具。同时，也学习和使用了一些前端框架如：angular、reactjs等。<br/><b>成果：</b><ul><li>做了两个商城类的pc端。包括用户端端和管理后台页面绘制。还用Angular基于html5做了其中一个产品的商家端Webapp,以及参与了微信公众号的混合开发。</li><li>利用nodejs一系列工具实现了前端代码性能优化精简。实现了自动打包发版部署测试环境。 探索并设计了适用于复杂的产品NativeJS的前端架构。</li><li>同时，利用工作之余探索并实现了前端自动化测试。</li></ul>"
    },
    {
      "time":"2014年",
      "title":"北京创杰恒远自动化有限公司",
      "intro":"前端开发",
      "description":"14年年初，来到北京，就职于北京创杰恒远自动化有限公司。从事前端开发方面工作。<br/><b>成果：</b>完成了一个官网网站的pc及管理后台的前端工作。与此同时，养成了以产品的思维来开展工作的习惯。 "
    },
    {
      "time":"",
      "title":"在湖北武汉工作",
      "intro":"其中包括半年的实习时间",
      "description":"毕业于武汉大学珞珈学院。在武汉工作一年。期间，在武汉百度分公司实习整合营销及网站的制作(校企合作),主要精力用于钻研学习SEM,SEO以及基本的网站模块开发及后台管理：Div+CSS。与此同时，学会了页面布局以及SEO,SEM之类营销型网站开发。"
    }

  ],
  "skill":[
    {
      "name":"Div+CSS",
      "percent":"90%"
    },
    {
      "name":"javascript+JQ",
      "percent":"80%"
    },
    {
      "name":"Html5+CSS3",
      "percent":"80%"
    },
    {
      "name":"PhotoShop",
      "percent":"70%"
    },
    {
      "name":"gulp+webpack+scss+less",
      "percent":"80%"
    },
    {
      "name":"Swiper+AngularJS+React",
      "percent":"50%"
    }
  ],
  "project":[
    {
      "time":"2016.5",
      "title":"红木家具商城(Webapp)",
      "intro":"框架开发的学习与研究",
      "description":"运用Angular框架搭建前端整体架构,制作前端静态资源目录结构和代码的发布流程,使用模板,把Html解析到DOM中,遍历DOM,指令操作DOM,依赖注入,创建自定义指令,装饰元素,除此之外，我们还利用HBuilder和PhoneGap基于前端技术制作老师移动端分别打包成了android和ios应用。<br/><b>实现的主要功能：</b><ul><li>用户登录注册以及用户管理。</li><li>发布新产品及供应信息,动态资讯更新</li><li>针对注册用户订购网站会员的订单系统。</li><li>商户系统。</li></ul>"
    },
    {
      "time":"2015底",
      "title":"英伦时光微网站",
      "intro":"一个附近在线商店产品",
      "description":"这个产品是前后端混合开发的。自己写的PHP连接数据库。完成了线上订购美食产品的一个网站和管理订单."
    },
    {
      "time":"2015",
      "title":"文萍百货",
      "intro":"一个百货批发在线商城",
      "description":"在此期间参与了一个在线商城包括商户端、用户端以及商城管理后台。pc端是基于Jquery制作，其他部分是基于一些其他插件利用gulp等一系列构建完成。<br/><b>实现的主要功能：</b><ul><li>商户端：根据现有内容库发布、供应产品。管理产品等。</li><li>用户端：查看和订购产品。</li><li>管理后台：管理商品及商城系统维护等。</li></ul>"
    },
    {
      "time":"2015.11-2016.08",
      "title":"品藏红木PC商城",
      "intro":"一个红木家具线上线下商城产品",
      "description":"与之前的听说通类似。如果之前的产品是淘宝模式，那么这个产品就是京东模式。同样包括用户端，商户端及管理后台。"
    }
  ],
  "usually":[
    {
      "name":"GitHub",
      "link":"",
      "description":"分享一些我的小作品 结交志同道合的朋友"
    },
    {
      "name":"知乎",
      "link":"",
      "description":"搜索解决一些疑问 探索新奇"
    },
    {
      "name":"MDN",
      "link":"",
      "description":"查阅一些技术文档"
    },
    {
      "name":"Behance",
      "description":"寻找灵感探索新奇"
    },
    {
      "name":"Dribbble",
      "link":"",
      "description":"寻找灵感探索新奇"
    },
    {
      "name":"CodePen",
      "link":"",
      "description":"探索和分享好的代码"
    }
  ]
}